simpley/__init__.py
simpley/console.py
simpley/file.py
simpley-1.1.4.dist-info/METADATA
simpley-1.1.4.dist-info/WHEEL
simpley-1.1.4.dist-info/RECORD
